weathermap/WeatherCache.py
weathermap/__init__.py
weathermap/locationtrack.py
weathermap/weathermap.py
weathermap-1.0.8.dist-info/LICENSE
weathermap-1.0.8.dist-info/METADATA
weathermap-1.0.8.dist-info/WHEEL
weathermap-1.0.8.dist-info/top_level.txt
weathermap-1.0.8.dist-info/RECORD
