Metadata-Version: 2.1
Name: weathermap
Version: 1.0.8
Summary: Openweathermap api simplified
Home-page: https://github.com/savan2508/WeatherApp
Author: Savan Patel
Author-email: sawanpatel2508@gmail.com
License: MIT
Keywords: weather,forecast,openweathermap,openweather
Classifier: Development Status :: 3 - Alpha
Classifier: Intended Audience :: Developers
Classifier: License :: OSI Approved :: MIT License
Classifier: Programming Language :: Python :: 3
Classifier: Programming Language :: Python :: 3.6
Classifier: Programming Language :: Python :: 3.7
Classifier: Programming Language :: Python :: 3.8
Classifier: Programming Language :: Python :: 3.9
Classifier: Programming Language :: Python :: 3.10
Classifier: Programming Language :: Python :: 3.11
License-File: LICENSE
Requires-Dist: requests
Requires-Dist: ipinfo (~=4.4.2)
Requires-Dist: geocoder (~=1.38.1)
